{
  "skills": [
    {
      "title": "MERN Stack",
      "link": "#"
    },
    {
      "title": "NodeJS",
      "link": "#"
    },
    {
      "title": "ReactJS",
      "link": "#"
    },
    {
      "title": "NextJS",
      "link": "#"
    },
    {
      "title": "ExpressJS",
      "link": "#"
    },
    {
      "title": "Python",
      "link": "#"
    },
    {
      "title": "Django",
      "link": "#"
    },
    {
      "title": "HTML/CSS",
      "link": "#"
    },
    {
      "title": "Java",
      "link": "#"
    },
    {
      "title": "JavaScript",
      "link": "#"
    },
    {
      "title": "C/C++",
      "link": "#"
    },
    {
      "title": "OOPs",
      "link": "#"
    },
    {
      "title": "REST API",
      "link": "#"
    },
    {
      "title": "DBMS - MongoDB",
      "link": "#"
    },
    {
      "title": "DBMS - MySQL",
      "link": "#"
    },
    {
      "title": "DSA Problem Solving",
      "link": "#"
    },
    {
      "title": "Bootstrap",
      "link": "#"
    },
    {
      "title": "Tailwind CSS",
      "link": "#"
    }
  ]
}
